{
  "api": {
    "helianthusAPI": {
      "service": "AppSync",
      "providerPlugin": "awscloudformation",
      "output": {
        "authConfig": {
          "defaultAuthentication": {
            "authenticationType": "API_KEY",
            "apiKeyConfig": {
              "apiKeyExpirationDays": 365,
              "description": "api access"
            }
          },
          "additionalAuthenticationProviders": []
        }
      }
    }
  },
  "hosting": {
    "amplifyhosting": {
      "service": "amplifyhosting",
      "type": "cicd",
      "lastPushTimeStamp": "2021-02-20T19:24:37.571Z"
    }
  }
}